setup.cfg
setup.py
bin/torrentcatcher
torrentcatcher/__init__.py
torrentcatcher/torrentcatcher.py
torrentcatcher/update.py
torrentcatcher.egg-info/PKG-INFO
torrentcatcher.egg-info/SOURCES.txt
torrentcatcher.egg-info/dependency_links.txt
torrentcatcher.egg-info/requires.txt
torrentcatcher.egg-info/top_level.txt