Metadata-Version: 1.1
Name: torrentcatcher
Version: 3.3.0
Summary: Takes torrent or magnet links from rss feeds you provide, parses them and sends them to transmission.
Home-page: http://archangelic.github.io/torrentcatcher/
Author: Michael Hancock
Author-email: michaelhancock89@gmail.com
License: GPLv3
Download-URL: https://github.com/archangelic/torrentcatcher/tarball/v3.3.0
Keywords: torrent,rss,transmission
Platform: UNKNOWN
Classifier: Environment :: Console
Classifier: Intended Audience :: End Users/Desktop
Classifier: Topic :: Internet
Classifier: License :: OSI Approved :: GNU General Public License v3 (GPLv3)
Classifier: Programming Language :: Python
Classifier: Natural Language :: English
Classifier: Operating System :: POSIX :: Linux
